pegma/AppClasses.py
pegma/HelpSystem.py
pegma/Main_icons_rc.py
pegma/UiClasses.py
pegma/__init__.py
pegma/docs_rc.py
pegma/main.py
pegma/pgmfigureoptions.py
pegma/plotConfig.py
pegma/defaultConfigs/_designSpec.rc
pegma/defaultConfigs/_fsAmp.rc
pegma/defaultConfigs/_fsPhase.rc
pegma/defaultConfigs/_fsUnwrappedPhase.rc
pegma/defaultConfigs/_iits.rc
pegma/defaultConfigs/_its.rc
pegma/defaultConfigs/_psAmp.rc
pegma/defaultConfigs/_psa.rc
pegma/defaultConfigs/_stretchedFsConfig.rc
pegma/defaultConfigs/_stretchedRsConfig.rc
pegma/defaultConfigs/_stretchedTsConfig.rc
pegma/defaultConfigs/_tripartite.rc
pegma/defaultConfigs/_ts.rc
pegma/ui/Main_icons_rc.py
pegma/ui/__init__.py
pegma/ui/docs_rc.py
pegma/ui/mainwindow_ui.py
pegma/ui/rc_docs.py
pegma/ui/ui_mainwindow.py
pegma-1.0.11.dist-info/LICENSE
pegma-1.0.11.dist-info/METADATA
pegma-1.0.11.dist-info/WHEEL
pegma-1.0.11.dist-info/entry_points.txt
pegma-1.0.11.dist-info/top_level.txt
pegma-1.0.11.dist-info/RECORD
