Metadata-Version: 2.1
Name: pegma
Version: 1.0.11
Summary: Package for Exploratory Ground Motion Analysis
Home-page: https://github.com/dbpatankar/pegma
Author: Digvijay Patankar
Author-email: dbpatankar@gmail.com
License: GNU GPLv3
Classifier: Development Status :: 4 - Beta
Classifier: Intended Audience :: Science/Research
Classifier: License :: OSI Approved :: GNU General Public License v3 (GPLv3)
Classifier: Operating System :: OS Independent
Classifier: Programming Language :: Python :: 3.6
Classifier: Programming Language :: Python :: 3.7
Classifier: Programming Language :: Python :: 3.8
Classifier: Programming Language :: Python :: 3.9
Classifier: Programming Language :: Python :: 3.10
Classifier: Programming Language :: Python :: 3.11
Requires-Python: >=3.6
License-File: LICENSE
Requires-Dist: pyside6
Requires-Dist: earthquakepy
Requires-Dist: matplotlib
Requires-Dist: numpy
Requires-Dist: scipy
